innit/__init__.py
innit/cli.py
innit/model.py
innit/onnx_runner.py
innit-0.0.1a0.dist-info/licenses/LICENSE
innit-0.0.1a0.dist-info/METADATA
innit-0.0.1a0.dist-info/WHEEL
innit-0.0.1a0.dist-info/entry_points.txt
innit-0.0.1a0.dist-info/top_level.txt
innit-0.0.1a0.dist-info/RECORD
